breakfast_puzzles.py
breakfast_puzzles-0.2.5.dist-info/entry_points.txt
breakfast_puzzles-0.2.5.dist-info/WHEEL
breakfast_puzzles-0.2.5.dist-info/METADATA
breakfast_puzzles-0.2.5.dist-info/RECORD
