Metadata-Version: 2.3
Name: breakfast-puzzles
Version: 0.2.5
Summary: Breakfast Puzzles is a script for laying out a selection of puzzles from
Author: Tom Fryers
Requires-Python: >=3.8
Classifier: Development Status :: 4 - Beta
Classifier: License :: OSI Approved :: GNU General Public License v3 or later (GPLv3+)
Classifier: Natural Language :: English
Classifier: Operating System :: POSIX :: Linux
Classifier: Programming Language :: Python :: 3
Project-URL: Home, https://gitlab.com/Tom_Fryers/breakfast-puzzles
